cds/__init__.py
cds/api_client.py
cds/configuration.py
cds/rest.py
cds/api/__init__.py
cds/api/accounts_api.py
cds/api/banking_api.py
cds/api/common_api.py
cds/api/customer_api.py
cds/api/direct_debits_api.py
cds/api/discovery_api.py
cds/api/payees_api.py
cds/api/products_api.py
cds/api/scheduled_payments_api.py
cds/models/__init__.py
cds/models/banking_account.py
cds/models/banking_account_detail.py
cds/models/banking_authorised_entity.py
cds/models/banking_balance.py
cds/models/banking_balance_purse.py
cds/models/banking_biller_payee.py
cds/models/banking_credit_card_account.py
cds/models/banking_direct_debit.py
cds/models/banking_domestic_payee.py
cds/models/banking_domestic_payee_account.py
cds/models/banking_domestic_payee_card.py
cds/models/banking_domestic_payee_pay_id.py
cds/models/banking_international_payee.py
cds/models/banking_international_payee_bank_details.py
cds/models/banking_international_payee_bank_details_bank_address.py
cds/models/banking_international_payee_beneficiary_details.py
cds/models/banking_loan_account.py
cds/models/banking_payee.py
cds/models/banking_payee_detail.py
cds/models/banking_product_bundle.py
cds/models/banking_product_category.py
cds/models/banking_product_constraint.py
cds/models/banking_product_deposit_rate.py
cds/models/banking_product_detail.py
cds/models/banking_product_discount.py
cds/models/banking_product_discount_eligibility.py
cds/models/banking_product_eligibility.py
cds/models/banking_product_feature.py
cds/models/banking_product_fee.py
cds/models/banking_product_lending_rate.py
cds/models/banking_product_rate_condition.py
cds/models/banking_product_rate_tier.py
cds/models/banking_product_rate_tier_sub_tier.py
cds/models/banking_product_v2.py
cds/models/banking_product_v2_additional_information.py
cds/models/banking_product_v2_card_art.py
cds/models/banking_scheduled_payment.py
cds/models/banking_scheduled_payment_from.py
cds/models/banking_scheduled_payment_interval.py
cds_api_client-0.0.2.dist-info/LICENSE
cds_api_client-0.0.2.dist-info/METADATA
cds_api_client-0.0.2.dist-info/WHEEL
cds_api_client-0.0.2.dist-info/top_level.txt
cds_api_client-0.0.2.dist-info/RECORD
