Metadata-Version: 2.1
Name: cds-api-client
Version: 0.0.2
Summary: A Python client package for accessing data from an API that follows the Consumer Data Standards (CDS).
Home-page: https://github.com/stephenmccalman/cds-python-api-client
Author: Stephen McCalman
Author-email: cds-api-client@googlegroups.com
License: BSD
Keywords: Consumer Data Standards,Swagger
Platform: UNKNOWN
Classifier: Development Status :: 3 - Alpha
Classifier: Intended Audience :: Developers
Classifier: License :: OSI Approved :: BSD License
Classifier: Topic :: Software Development :: Build Tools
Classifier: Programming Language :: Python :: 3
Requires-Python: ~=3.4
Requires-Dist: certifi (>=2017.4.17)
Requires-Dist: python-dateutil (>=2.1)
Requires-Dist: urllib3 (>=1.23)
